django_csv2json/action.py
django_csv2json/funciones.py
django_csv2json-0.1.1.dist-info/METADATA
django_csv2json-0.1.1.dist-info/WHEEL
django_csv2json-0.1.1.dist-info/top_level.txt
django_csv2json-0.1.1.dist-info/RECORD
